pixitlib/__init__.py
pixitlib/consoleConnexion.py
pixitlib-0.1.6.dist-info/LICENSE
pixitlib-0.1.6.dist-info/METADATA
pixitlib-0.1.6.dist-info/WHEEL
pixitlib-0.1.6.dist-info/top_level.txt
pixitlib-0.1.6.dist-info/RECORD
