Metadata-Version: 2.2
Name: pixitlib
Version: 0.1.6
Summary: Une librairie pour aider les devs du projet pixit sur la connexion entre les jeux et la console.
Home-page: https://github.com/Kylian0Dragnir/pixitLib
Author: Mermin Kylian
Author-email: kylianmermin1@gmail.com
Classifier: Programming Language :: Python :: 3
Classifier: License :: OSI Approved :: MIT License
Classifier: Operating System :: OS Independent
Requires-Python: >=3.6
License-File: LICENSE
Dynamic: author
Dynamic: author-email
Dynamic: classifier
Dynamic: description
Dynamic: description-content-type
Dynamic: home-page
Dynamic: requires-python
Dynamic: summary
